Metadata-Version: 2.1
Name: pyacoustid
Version: 1.3.0
Summary: bindings for Chromaprint acoustic fingerprinting and the Acoustid API
Home-page: https://github.com/sampsyo/pyacoustid
Author: Adrian Sampson
Author-email: adrian@radbox.org
License: MIT
Platform: ALL
Classifier: Topic :: Multimedia :: Sound/Audio :: Conversion
Classifier: Intended Audience :: Developers
Classifier: Programming Language :: Python :: 2
Classifier: Programming Language :: Python :: 3
License-File: LICENSE
